willamette/__init__.py
willamette/app.py
willamette/app_util.py
willamette/cli/__init__.py
willamette/cli/db.py
willamette/config/__init__.py
willamette/config/flask_config.py
willamette/config/gunicorn_config.py
willamette/models/__init__.py
willamette/models/api_v1/__init__.py
willamette/models/api_v1/web_pages.py
willamette/models/api_v1/web_sites.py
willamette/views/__init__.py
willamette/views/api_v1/__init__.py
willamette/views/api_v1/web_pages.py
willamette/views/api_v1/web_sites.py
quaerere_willamette-0.1.2.dist-info/LICENSE.txt
quaerere_willamette-0.1.2.dist-info/METADATA
quaerere_willamette-0.1.2.dist-info/WHEEL
quaerere_willamette-0.1.2.dist-info/dependency_links.txt
quaerere_willamette-0.1.2.dist-info/entry_points.txt
quaerere_willamette-0.1.2.dist-info/top_level.txt
quaerere_willamette-0.1.2.dist-info/RECORD
