Metadata-Version: 2.1
Name: quaerere-willamette
Version: 0.1.2
Summary: A component of the Quaerere Platform
Home-page: https://github.com/QuaererePlatform/willamette
Author: Caitlyn O'Hanna
Author-email: ravenoak@virtualxistenz.com
License: AGPLv3+
Project-URL: Documentation, http://willamette.readthedocs.io/
Project-URL: Source Code, https://github.com/QuaererePlatform/willamette
Platform: UNKNOWN
Classifier: Development Status :: 2 - Pre-Alpha
Classifier: Environment :: Web Environment
Classifier: Framework :: Flask
Classifier: Intended Audience :: Science/Research
Classifier: License :: OSI Approved :: GNU Affero General Public License v3 or later (AGPLv3+)
Classifier: Operating System :: OS Independent
Classifier: Programming Language :: Python :: 3 :: Only
Classifier: Programming Language :: Python :: 3.6
Classifier: Programming Language :: Python :: 3.7
Classifier: Topic :: Scientific/Engineering :: Information Analysis
Classifier: Topic :: Text Processing :: Linguistic
Requires-Python: >=3.6
Requires-Dist: Flask (>=1.0.0)
Requires-Dist: Flask-arango-orm (>=0.1.1)
Requires-Dist: Flask-Classful (>=0.14.2)
Requires-Dist: flask-marshmallow (>=0.10.0)
Requires-Dist: marshmallow (<3,>=2.16.0)
Requires-Dist: python-arango (<5,>=4.4)
Requires-Dist: quaerere-base-flask (>=0.3.0)
Requires-Dist: quaerere-willamette-common (>=0.2.1.post1)
